README.md
keyplus-cli
setup.py
keyplus/__init__.py
keyplus/cdata_types.py
keyplus/chip_id.py
keyplus/debug.py
keyplus/device_info.py
keyplus/error_table.py
keyplus/exceptions.py
keyplus/keyboard.py
keyplus/settings.py
keyplus/usb_ids.py
keyplus/version.py
keyplus.egg-info/PKG-INFO
keyplus.egg-info/SOURCES.txt
keyplus.egg-info/dependency_links.txt
keyplus.egg-info/not-zip-safe
keyplus.egg-info/requires.txt
keyplus.egg-info/top_level.txt
keyplus/constants/__init__.py
keyplus/constants/error.py
keyplus/constants/rf.py
keyplus/constants/scan_mode.py
keyplus/constants/settings.py
keyplus/constants/usb.py
keyplus/constants/usb_commands.py
keyplus/io_map/__init__.py
keyplus/io_map/common.py
keyplus/io_map/io_mapper.py
keyplus/io_map/mega.py
keyplus/io_map/xmega.py
keyplus/keycodes/__init__.py
keyplus/keycodes/keycode_mapper.py
keyplus/keycodes/keycodes.py
keyplus/keycodes/mapped_keycodes.py
keyplus/layout/__init__.py
keyplus/layout/debounce_profiles.py
keyplus/layout/device.py
keyplus/layout/ekc_data.py
keyplus/layout/keyboard_layout.py
keyplus/layout/layout.py
keyplus/layout/parser.py
keyplus/layout/parser_info.py
keyplus/layout/rf_settings.py
keyplus/layout/scan_mode.py
keyplus/layout/user_keycodes.py
keyplus/utility/__init__.py
keyplus/utility/crc16.py
keyplus/utility/round_keys.py