Metadata-Version: 1.0
Name: keyplus
Version: 0.3.0
Summary: Python library for interfacing with keyplus keyboards.
Home-page: http://github.com/ahtn/keyplus
Author: jem
Author-email: jem@seethis.link
License: MIT
Keywords: keyboard,usb,hid
Platform: UNKNOWN
